airtime/__init__.py
airtime/teams_analyzer.py
airtime/zoom_analyzer.py
airtime/tests/__init__.py
airtime/tests/test_teams_analyzer.py
airtime/tests/test_zoom_analyzer.py
airtime-1.0.2.dist-info/LICENSE
airtime-1.0.2.dist-info/METADATA
airtime-1.0.2.dist-info/WHEEL
airtime-1.0.2.dist-info/top_level.txt
airtime-1.0.2.dist-info/RECORD
