Metadata-Version: 2.1
Name: airtime
Version: 1.0.2
Summary: A package for analyzing transcripts
Home-page: https://github.com/jcontd/airtime
Author: Jana M. Perkins
Author-email: mailroom@jcontd.com
License: GNU Affero General Public License v3
Classifier: Development Status :: 3 - Alpha
Classifier: Intended Audience :: Developers
Classifier: Intended Audience :: Science/Research
Classifier: License :: OSI Approved :: GNU Affero General Public License v3
Classifier: Programming Language :: Python :: 3
Classifier: Programming Language :: Python :: 3.7
Classifier: Programming Language :: Python :: 3.8
Classifier: Programming Language :: Python :: 3.9
Classifier: Topic :: Text Processing
Classifier: Topic :: Utilities
License-File: LICENSE
